idkwtfit/__init__.py
idkwtfit/html2text.py
idkwtfit/random_color.py
idkwtfit/models/__init__.py
idkwtfit/models/color.py
idkwtfit-0.3.1.dist-info/LICENSE
idkwtfit-0.3.1.dist-info/METADATA
idkwtfit-0.3.1.dist-info/WHEEL
idkwtfit-0.3.1.dist-info/top_level.txt
idkwtfit-0.3.1.dist-info/RECORD
