Metadata-Version: 2.1
Name: idkwtfit
Version: 0.3.1
Summary: I don't know what the fuck is this
Home-page: UNKNOWN
Author: ombe1229
Author-email: h3236516@gmail.com
License: Apache 2.0
Platform: UNKNOWN
License-File: LICENSE
